libglfw.so.3.3
libtinyobjloader.so
libRendererCpp.so
libtinyobjloader.so.1
libspdlog.so
libtinyobjloader.so.1.0.4
renderer_bindings.cpython-38-x86_64-linux-gnu.so
libspdlog.so.1.11.0
libglfw.so.3
libglfw.so
libUtilsCpp.so
libspdlog.so.1.11
wp_renderer.libs/libGLdispatch-228223fa.so.0.0.0
wp_renderer.libs/libEGL-976e38d5.so.1.1.0
renderer/__init__.py
wp_renderer-0.3.10.dist-info/WHEEL
wp_renderer-0.3.10.dist-info/LICENSE
wp_renderer-0.3.10.dist-info/RECORD
wp_renderer-0.3.10.dist-info/top_level.txt
wp_renderer-0.3.10.dist-info/METADATA
