Metadata-Version: 2.1
Name: wp-renderer
Version: 0.3.10
Summary: A minimal renderer for prototyping 3D applications
Home-page: https://github.com/wpumacay/renderer
Author: Wilbert Santos Pumacay Huallpa
Author-email: wpumacay@gmail.com
License: MIT License
Keywords: graphics opengl
Classifier: License :: OSI Approved :: MIT License
Classifier: Operating System :: POSIX :: Linux
Classifier: Programming Language :: Python :: 3
Classifier: Programming Language :: Python :: 3 :: Only
Classifier: Programming Language :: Python :: Implementation :: CPython
Requires-Python: >=3.7
License-File: LICENSE
